alt_pytest_asyncio/__init__.py
alt_pytest_asyncio/base.py
alt_pytest_asyncio/converter.py
alt_pytest_asyncio/enable.py
alt_pytest_asyncio/errors.py
alt_pytest_asyncio/loop_manager.py
alt_pytest_asyncio/machinery.py
alt_pytest_asyncio/plugin.py
alt_pytest_asyncio/protocols.py
alt_pytest_asyncio/py.typed
alt_pytest_asyncio/version.py
alt_pytest_asyncio-0.9.3.dist-info/METADATA
alt_pytest_asyncio-0.9.3.dist-info/WHEEL
alt_pytest_asyncio-0.9.3.dist-info/entry_points.txt
alt_pytest_asyncio-0.9.3.dist-info/licenses/LICENSE
alt_pytest_asyncio-0.9.3.dist-info/RECORD
