Metadata-Version: 2.4
Name: alt-pytest-asyncio
Version: 0.9.3
Summary: Alternative pytest plugin to pytest-asyncio
Project-URL: Homepage, https://github.com/delfick/alt-pytest-asyncio
Author-email: Stephen Moore <delfick755@gmail.com>
License: MIT
License-File: LICENSE
Classifier: Framework :: Pytest
Classifier: Topic :: Software Development :: Testing
Requires-Python: >=3.11
Requires-Dist: pytest>=8.0.0
Provides-Extra: dev
Requires-Dist: alt-pytest-asyncio-test-driver; extra == 'dev'
Requires-Dist: tools; extra == 'dev'
Provides-Extra: tools
Requires-Dist: tools; extra == 'tools'
